{
  "examples": [
    {
      "example": 1,
      "input": "0 0 2 0 0 6 0 0 0 0\n0 0 0 0 0 0 0 0 0 0\n2 0 0 0 0 0 0 0 0 0\n0 0 0 0 0 0 0 0 0 0\n0 0 0 0 0 0 0 0 0 6\n0 0 0 4 0 0 0 0 0 0\n0 0 0 0 0 0 0 0 0 0\n0 0 0 0 0 0 0 0 0 0\n0 0 0 0 0 0 0 0 0 0\n0 0 0 0 0 0 0 4 0 0",
      "expected_output": "0 0 2 0 0 6 0 0 0 0\n0 2 0 0 0 0 6 0 0 0\n2 0 0 0 0 0 0 6 0 0\n0 0 0 0 0 0 0 0 6 0\n0 0 0 0 0 0 0 0 0 6\n0 0 0 4 0 0 0 0 0 0\n0 0 0 0 4 0 0 0 0 0\n0 0 0 0 0 4 0 0 0 0\n0 0 0 0 0 0 4 0 0 0\n0 0 0 0 0 0 0 4 0 0",
      "transformed_output": "0 0 2 0 0 6 0 0 0 0\n0 0 2 0 0 6 0 0 0 0\n2 0 2 0 0 6 0 0 0 0\n2 0 2 0 0 6 0 0 0 0\n2 0 2 0 0 6 0 0 0 6\n2 0 2 4 0 6 0 0 0 6\n2 0 2 4 0 6 0 0 0 6\n2 0 2 4 0 6 0 0 0 6\n2 0 2 4 0 6 0 0 0 6\n2 0 2 4 0 6 0 4 0 6",
      "size_correct": true,
      "color_palette_correct": true,
      "correct_pixel_counts": false,
      "pixels_off": 40,
      "percent_correct": 60.0,
      "match": false
    },
    {
      "example": 2,
      "input": "9 0 0 0 0 0 0 3 0 0\n0 0 0 0 0 0 0 0 0 0\n0 0 0 0 0 0 8 0 0 3\n0 0 0 9 0 0 0 0 0 0\n0 0 0 0 0 0 0 0 0 0\n0 0 0 0 0 7 0 0 0 0\n0 0 0 0 0 0 0 0 0 0\n0 8 0 0 0 0 0 0 0 0\n0 0 0 0 0 0 0 0 0 0\n0 0 0 0 0 0 0 0 0 7",
      "expected_output": "9 0 0 0 0 0 0 3 0 0\n0 9 0 0 0 0 0 0 3 0\n0 0 9 0 0 0 8 0 0 3\n0 0 0 9 0 8 0 0 0 0\n0 0 0 0 8 0 0 0 0 0\n0 0 0 8 0 7 0 0 0 0\n0 0 8 0 0 0 7 0 0 0\n0 8 0 0 0 0 0 7 0 0\n0 0 0 0 0 0 0 0 7 0\n0 0 0 0 0 0 0 0 0 7",
      "transformed_output": "9 0 0 0 0 0 0 3 0 0\n9 0 0 0 0 0 0 3 0 0\n9 0 0 0 0 0 8 3 0 3\n9 0 0 9 0 0 8 3 0 3\n9 0 0 9 0 0 8 3 0 3\n9 0 0 9 0 7 8 3 0 3\n9 0 0 9 0 7 8 3 0 3\n9 8 0 9 0 7 8 3 0 3\n9 8 0 9 0 7 8 3 0 3\n9 8 0 9 0 7 8 3 0 3",
      "size_correct": true,
      "color_palette_correct": true,
      "correct_pixel_counts": false,
      "pixels_off": 51,
      "percent_correct": 49.0,
      "match": false
    },
    {
      "example": 3,
      "input": "0 0 0 6 0 8 0 0 0 0\n0 0 0 0 0 0 0 0 0 0\n0 0 4 0 0 0 0 0 0 0\n6 0 0 0 0 0 0 0 0 0\n0 0 0 0 0 0 0 0 0 8\n0 0 0 0 9 0 0 0 0 0\n0 0 0 0 0 0 4 0 0 0\n0 0 0 0 0 0 0 0 0 0\n0 0 0 0 0 0 0 0 0 0\n9 0 0 0 0 0 0 0 0 0",
      "expected_output": "0 0 0 6 0 8 0 0 0 0\n0 0 6 0 0 0 8 0 0 0\n0 6 4 0 0 0 0 8 0 0\n6 0 0 4 0 0 0 0 8 0\n0 0 0 0 4 0 0 0 0 8\n0 0 0 0 9 4 0 0 0 0\n0 0 0 9 0 0 4 0 0 0\n0 0 9 0 0 0 0 0 0 0\n0 9 0 0 0 0 0 0 0 0\n9 0 0 0 0 0 0 0 0 0",
      "transformed_output": "0 0 0 6 0 8 0 0 0 0\n0 0 0 6 0 8 0 0 0 0\n0 0 4 6 0 8 0 0 0 0\n6 0 4 6 0 8 0 0 0 0\n6 0 4 6 0 8 0 0 0 8\n6 0 4 6 9 8 0 0 0 8\n6 0 4 6 9 8 4 0 0 8\n6 0 4 6 9 8 4 0 0 8\n6 0 4 6 9 8 4 0 0 8\n6 0 4 6 9 8 4 0 0 8",
      "size_correct": true,
      "color_palette_correct": true,
      "correct_pixel_counts": false,
      "pixels_off": 50,
      "percent_correct": 50.0,
      "match": false
    }
  ]
}