{
  "train": {
    "trials": [
      {
        "match": false,
        "score": 44.44444444444443,
        "input": "8 8 0 0 0 0 0 0 0\n0 0 8 0 0 0 0 0 0\n8 0 0 0 0 0 0 0 0\n0 0 0 0 0 0 0 0 0\n0 0 0 0 0 0 0 0 0\n0 0 0 0 0 0 0 0 0\n0 0 0 0 0 0 0 0 0\n0 0 0 0 0 0 0 0 0\n0 0 0 0 0 0 0 0 0",
        "expected_output": "8 8 0 8 8 0 0 0 0\n0 0 8 0 0 8 0 0 0\n8 0 0 8 0 0 0 0 0\n0 0 0 0 0 0 8 8 0\n0 0 0 0 0 0 0 0 8\n0 0 0 0 0 0 8 0 0\n8 8 0 0 0 0 0 0 0\n0 0 8 0 0 0 0 0 0\n8 0 0 0 0 0 0 0 0",
        "transformed_output": "8 8 8 8 0 0 0 0 0\n8 8 8 8 0 0 0 0 0\n8 8 8 8 0 0 0 0 0\n8 8 0 0 0 0 0 0 0\n0 0 0 0 0 0 0 0 0\n0 0 0 0 0 0 0 0 0\n0 0 0 0 0 0 0 0 0\n0 0 0 0 0 0 0 0 0\n0 0 0 0 0 0 0 0 0",
        "size_correct": true,
        "color_palette_correct": true,
        "color_count_correct": false,
        "pixels_off": 18,
        "percent_correct": 77.77777777777779
      },
      {
        "match": false,
        "score": 54.32098765432099,
        "input": "0 0 0 0 0 0 0 0 0\n0 0 0 0 0 0 0 0 0\n0 0 0 0 0 0 0 0 0\n0 0 0 0 0 7 0 0 0\n0 0 0 0 7 7 0 0 0\n0 0 0 7 0 0 0 0 0\n0 0 0 0 0 0 0 0 0\n0 0 0 0 0 0 0 0 0\n0 0 0 0 0 0 0 0 0",
        "expected_output": "0 0 0 0 0 0 0 0 7\n0 0 0 0 0 0 0 7 7\n0 0 0 0 0 0 7 0 0\n0 0 0 0 0 7 0 0 7\n0 0 0 0 7 7 0 7 7\n0 0 0 7 0 0 7 0 0\n0 0 7 0 0 0 0 0 0\n0 7 7 0 0 0 0 0 0\n7 0 0 0 0 0 0 0 0",
        "transformed_output": "0 0 0 0 0 0 0 0 0\n0 0 0 0 0 0 0 0 0\n0 0 0 0 7 7 7 0 0\n0 0 0 7 7 7 7 0 0\n0 0 7 7 7 7 7 0 0\n0 0 7 7 7 7 7 0 0\n0 0 7 7 7 0 0 0 0\n0 0 0 0 0 0 0 0 0\n0 0 0 0 0 0 0 0 0",
        "size_correct": true,
        "color_palette_correct": true,
        "color_count_correct": false,
        "pixels_off": 22,
        "percent_correct": 72.8395061728395
      },
      {
        "match": false,
        "score": 83.9506172839506,
        "input": "0 0 0 0 6 0 0 0 0\n0 0 0 6 0 6 0 0 0\n0 0 0 6 6 0 0 0 0\n0 0 0 0 0 0 0 0 0\n0 0 0 0 0 0 0 0 0\n0 0 0 0 0 0 0 0 0\n0 0 0 0 0 0 0 0 0\n0 0 0 0 0 0 0 0 0\n0 0 0 0 0 0 0 0 0",
        "expected_output": "0 0 0 0 6 0 0 0 0\n0 0 0 6 0 6 0 0 0\n0 0 0 6 6 0 0 0 0\n0 6 0 0 0 0 0 6 0\n6 0 6 0 0 0 6 0 6\n6 6 0 0 0 0 6 6 0\n0 6 0 0 6 0 0 0 0\n6 0 6 6 0 6 0 0 0\n6 6 0 6 6 0 0 0 0",
        "transformed_output": "0 0 6 6 6 6 6 0 0\n0 0 6 6 6 6 6 0 0\n0 0 6 6 6 6 6 0 0\n0 0 6 6 6 6 0 0 0\n0 0 0 0 0 0 0 0 0\n0 0 0 0 0 0 0 0 0\n0 0 0 0 0 0 0 0 0\n0 0 0 0 0 0 0 0 0\n0 0 0 0 0 0 0 0 0",
        "size_correct": true,
        "color_palette_correct": true,
        "color_count_correct": false,
        "pixels_off": 34,
        "percent_correct": 58.0246913580247
      }
    ]
  },
  "test": null,
  "total_score": 182.71604938271602,
  "average_score": 60.905349794238674
}