{
  "train": {
    "trials": [
      {
        "match": true,
        "score": 0,
        "input": "2 2 2 2 2 2 2 2 2 2 0 0 0 0 0 3 0",
        "expected_output": "0 0 0 0 0 2 2 2 2 2 2 2 2 2 2 3 0",
        "transformed_output": "0 0 0 0 0 2 2 2 2 2 2 2 2 2 2 3 0",
        "size_correct": true,
        "color_palette_correct": true,
        "color_count_correct": true,
        "pixels_off": 0,
        "percent_correct": 100.0
      },
      {
        "match": true,
        "score": 0,
        "input": "0 0 0 0 0 0 0 5 5 5 5 5 0 0 0 3 0",
        "expected_output": "0 0 0 0 0 0 0 0 0 0 5 5 5 5 5 3 0",
        "transformed_output": "0 0 0 0 0 0 0 0 0 0 5 5 5 5 5 3 0",
        "size_correct": true,
        "color_palette_correct": true,
        "color_count_correct": true,
        "pixels_off": 0,
        "percent_correct": 100.0
      },
      {
        "match": true,
        "score": 0,
        "input": "0 8 8 8 8 8 8 8 8 0 0 0 0 0 0 0 3",
        "expected_output": "0 0 0 0 0 0 0 0 8 8 8 8 8 8 8 8 3",
        "transformed_output": "0 0 0 0 0 0 0 0 8 8 8 8 8 8 8 8 3",
        "size_correct": true,
        "color_palette_correct": true,
        "color_count_correct": true,
        "pixels_off": 0,
        "percent_correct": 100.0
      }
    ],
    "error": null
  },
  "test": {
    "trials": [
      {
        "match": true,
        "score": 0,
        "input": "0 5 5 5 5 5 5 5 5 5 5 5 0 0 0 0 3",
        "expected_output": "0 0 0 0 0 5 5 5 5 5 5 5 5 5 5 5 3",
        "transformed_output": "0 0 0 0 0 5 5 5 5 5 5 5 5 5 5 5 3",
        "size_correct": true,
        "color_palette_correct": true,
        "color_count_correct": true,
        "pixels_off": 0,
        "percent_correct": 100.0
      }
    ],
    "error": null
  },
  "total_score": 0,
  "average_score": 0.0
}